[{"schema": "TurboMobsAllaSeedNpc", "npc_id": 176095, "id": 176095, "name": "Bloodwretch", "points": [{"x": 1424.0, "y": 1325.0, "z": 19.0, "ph_names": ["a netherbian ravager", "a netherbian hive fiend", "a netherbian flesheater"], "chance": 28.0, "respawn_seconds": 1200, "source_url": "https://lazaruseq.com/alla/npcs/176095", "timer_source": "lazarus_alla"}], "source_url": "https://lazaruseq.com/alla/npcs/176095", "timer_source": "lazarus_alla"}, {"schema": "TurboMobsAllaSeedNpc", "npc_id": 176088, "id": 176088, "name": "Doomshade", "points": [], "source_url": "https://lazaruseq.com/alla/npcs/176088", "timer_source": "lazarus_alla"}, {"schema": "TurboMobsAllaSeedNpc", "npc_id": 176083, "id": 176083, "name": "Festersore", "points": [{"x": 699.0, "y": 2163.0, "z": 222.0, "ph_names": ["a netherbian infestor"], "chance": 5.0, "respawn_seconds": 1200, "source_url": "https://lazaruseq.com/alla/npcs/176083", "timer_source": "lazarus_alla"}], "source_url": "https://lazaruseq.com/alla/npcs/176083", "timer_source": "lazarus_alla"}, {"schema": "TurboMobsAllaSeedNpc", "npc_id": 176062, "id": 176062, "name": "Gantru Dralkenr", "points": [{"x": 1141.0, "y": 382.0, "z": 24.0, "ph_names": [], "chance": 100.0, "respawn_seconds": 14400, "source_url": "https://lazaruseq.com/alla/npcs/176062", "timer_source": "lazarus_alla"}], "source_url": "https://lazaruseq.com/alla/npcs/176062", "timer_source": "lazarus_alla"}, {"schema": "TurboMobsAllaSeedNpc", "npc_id": 176111, "id": 176111, "name": "Netherbian Swarmfiend", "points": [{"x": -1174.0, "y": -1111.0, "z": -14.0, "ph_names": [], "chance": 100.0, "respawn_seconds": 3600, "source_url": "https://lazaruseq.com/alla/npcs/176111", "timer_source": "lazarus_alla"}], "source_url": "https://lazaruseq.com/alla/npcs/176111", "timer_source": "lazarus_alla"}, {"schema": "TurboMobsAllaSeedNpc", "npc_id": 176002, "id": 176002, "name": "Rumblecrush", "points": [{"x": -738.0, "y": -1867.0, "z": 154.0, "ph_names": [], "chance": 100.0, "respawn_seconds": 22032, "source_url": "https://lazaruseq.com/alla/npcs/176002", "timer_source": "lazarus_alla"}], "source_url": "https://lazaruseq.com/alla/npcs/176002", "timer_source": "lazarus_alla"}]